hashedcolls/__init__.py
hashedcolls/hashedcolls.py
hashedcolls-1.1.1.dist-info/METADATA
hashedcolls-1.1.1.dist-info/WHEEL
hashedcolls-1.1.1.dist-info/top_level.txt
hashedcolls-1.1.1.dist-info/RECORD
