Metadata-Version: 2.1
Name: hashedcolls
Version: 1.1.1
Summary: Hashed dict/list collections
Author: @jedi2light
Author-email: jedi2light@jedi2light.moe
Maintainer: @jedi2light
Maintainer-email: jedi2light@jedi2light.moe
License: WTFPL
Project-URL: Source, https://gitlab.com/jedi2light/hashedcolls.git
Project-URL: Bug Tracker, https://gitlab.com/jedi2light/hashedcolls/issues
Classifier: Programming Language :: Python :: 3
Classifier: Operating System :: OS Independent
Requires-Python: >=3.6
